LICENSE
MANIFEST.in
README.rst
requirements-tests.txt
requirements.txt
setup.py
.tox/py2.7-rl-30/pip-selfcheck.json
.tox/py2.7-rl-30/lib/python2.7/site-packages/curriculum/templates/base_page.html
.tox/py2.7-rl-30/lib/python2.7/site-packages/curriculum/templates/base_pdf.html
.tox/py2.7-rl-30/lib/python2.7/site-packages/curriculum/templates/classic.html
.tox/py2.7-rl-30/lib/python2.7/site-packages/curriculum/templates/single_page.html
.tox/py2.7-rl-30/lib/python2.7/site-packages/factory_boy-2.6.0.dist-info/metadata.json
.tox/py2.7-rl-30/lib/python2.7/site-packages/factory_boy-2.6.0.dist-info/pbr.json
.tox/py2.7-rl-30/lib/python2.7/site-packages/pip-6.1.1.dist-info/metadata.json
.tox/py2.7-rl-30/lib/python2.7/site-packages/pip-6.1.1.dist-info/pbr.json
.tox/py2.7-rl-30/lib/python2.7/site-packages/setuptools-15.0.dist-info/metadata.json
.tox/py2.7-rl-30/lib/python2.7/site-packages/six-1.10.0.dist-info/metadata.json
.tox/py2.7-rl-30/lib/python2.7/site-packages/tests/testapp/fixtures/certification.json
.tox/py2.7-rl-30/lib/python2.7/site-packages/tests/testapp/fixtures/certification_item.json
.tox/py2.7-rl-30/lib/python2.7/site-packages/tests/testapp/fixtures/experience.json
.tox/py2.7-rl-30/lib/python2.7/site-packages/tests/testapp/fixtures/language.json
.tox/py2.7-rl-30/lib/python2.7/site-packages/tests/testapp/fixtures/language_item.json
.tox/py2.7-rl-30/lib/python2.7/site-packages/tests/testapp/fixtures/project.json
.tox/py2.7-rl-30/lib/python2.7/site-packages/tests/testapp/fixtures/project_item.json
.tox/py2.7-rl-30/lib/python2.7/site-packages/tests/testapp/fixtures/resume.json
.tox/py2.7-rl-30/lib/python2.7/site-packages/tests/testapp/fixtures/skill.json
.tox/py2.7-rl-30/lib/python2.7/site-packages/tests/testapp/fixtures/skill_item.json
.tox/py2.7-rl-30/lib/python2.7/site-packages/tests/testapp/fixtures/training.json
.tox/py2.7-rl-30/local/lib/python2.7/site-packages/curriculum/templates/base_page.html
.tox/py2.7-rl-30/local/lib/python2.7/site-packages/curriculum/templates/base_pdf.html
.tox/py2.7-rl-30/local/lib/python2.7/site-packages/curriculum/templates/classic.html
.tox/py2.7-rl-30/local/lib/python2.7/site-packages/curriculum/templates/single_page.html
.tox/py2.7-rl-30/local/lib/python2.7/site-packages/factory_boy-2.6.0.dist-info/metadata.json
.tox/py2.7-rl-30/local/lib/python2.7/site-packages/factory_boy-2.6.0.dist-info/pbr.json
.tox/py2.7-rl-30/local/lib/python2.7/site-packages/pip-6.1.1.dist-info/metadata.json
.tox/py2.7-rl-30/local/lib/python2.7/site-packages/pip-6.1.1.dist-info/pbr.json
.tox/py2.7-rl-30/local/lib/python2.7/site-packages/setuptools-15.0.dist-info/metadata.json
.tox/py2.7-rl-30/local/lib/python2.7/site-packages/six-1.10.0.dist-info/metadata.json
.tox/py2.7-rl-30/local/lib/python2.7/site-packages/tests/testapp/fixtures/certification.json
.tox/py2.7-rl-30/local/lib/python2.7/site-packages/tests/testapp/fixtures/certification_item.json
.tox/py2.7-rl-30/local/lib/python2.7/site-packages/tests/testapp/fixtures/experience.json
.tox/py2.7-rl27-django1.8/lib/python2.7/site-packages/Django-1.8.5.dist-info/metadata.json
.tox/py2.7-rl27-django1.8/lib/python2.7/site-packages/astroid-1.3.8.dist-info/metadata.json
.tox/py2.7-rl27-django1.8/lib/python2.7/site-packages/factory_boy-2.6.0.dist-info/metadata.json
.tox/py2.7-rl27-django1.8/lib/python2.7/site-packages/factory_boy-2.6.0.dist-info/pbr.json
.tox/py2.7-rl27-django1.8/lib/python2.7/site-packages/flake8-2.5.0.dist-info/metadata.json
.tox/py2.7-rl27-django1.8/lib/python2.7/site-packages/flake8-2.5.0.dist-info/pbr.json
.tox/py2.7-rl27-django1.8/lib/python2.7/site-packages/funcsigs-0.4.dist-info/pydist.json
.tox/py2.7-rl27-django1.8/lib/python2.7/site-packages/mccabe-0.3.1.dist-info/metadata.json
.tox/py2.7-rl27-django1.8/lib/python2.7/site-packages/mock-1.3.0.dist-info/metadata.json
.tox/py2.7-rl27-django1.8/lib/python2.7/site-packages/mock-1.3.0.dist-info/pbr.json
.tox/py2.7-rl27-django1.8/lib/python2.7/site-packages/pbr-1.8.1.dist-info/metadata.json
.tox/py2.7-rl27-django1.8/lib/python2.7/site-packages/pep8-1.6.2.dist-info/metadata.json
.tox/py2.7-rl27-django1.8/lib/python2.7/site-packages/pip-6.1.1.dist-info/metadata.json
.tox/py2.7-rl27-django1.8/lib/python2.7/site-packages/pip-6.1.1.dist-info/pbr.json
.tox/py2.7-rl27-django1.8/lib/python2.7/site-packages/pyflakes-1.0.0.dist-info/metadata.json
.tox/py2.7-rl27-django1.8/lib/python2.7/site-packages/pyflakes-1.0.0.dist-info/pbr.json
.tox/py2.7-rl27-django1.8/lib/python2.7/site-packages/pylint-1.4.4.dist-info/metadata.json
.tox/py2.7-rl27-django1.8/lib/python2.7/site-packages/setuptools-15.0.dist-info/metadata.json
.tox/py2.7-rl27-django1.8/lib/python2.7/site-packages/six-1.10.0.dist-info/metadata.json
.tox/py2.7-rl27-django1.8/local/lib/python2.7/site-packages/Django-1.8.5.dist-info/metadata.json
.tox/py2.7-rl27-django1.8/local/lib/python2.7/site-packages/astroid-1.3.8.dist-info/metadata.json
.tox/py2.7-rl27-django1.8/local/lib/python2.7/site-packages/factory_boy-2.6.0.dist-info/metadata.json
.tox/py2.7-rl27-django1.8/local/lib/python2.7/site-packages/factory_boy-2.6.0.dist-info/pbr.json
.tox/py2.7-rl27-django1.8/local/lib/python2.7/site-packages/flake8-2.5.0.dist-info/metadata.json
.tox/py2.7-rl27-django1.8/local/lib/python2.7/site-packages/flake8-2.5.0.dist-info/pbr.json
.tox/py2.7-rl27-django1.8/local/lib/python2.7/site-packages/funcsigs-0.4.dist-info/pydist.json
.tox/py2.7-rl27-django1.8/local/lib/python2.7/site-packages/mccabe-0.3.1.dist-info/metadata.json
.tox/py2.7-rl27-django1.8/local/lib/python2.7/site-packages/mock-1.3.0.dist-info/metadata.json
.tox/py2.7-rl27-django1.8/local/lib/python2.7/site-packages/mock-1.3.0.dist-info/pbr.json
.tox/py2.7-rl27-django1.8/local/lib/python2.7/site-packages/pbr-1.8.1.dist-info/metadata.json
.tox/py2.7-rl27-django1.8/local/lib/python2.7/site-packages/pep8-1.6.2.dist-info/metadata.json
.tox/py2.7-rl27-django1.8/local/lib/python2.7/site-packages/pip-6.1.1.dist-info/metadata.json
